astrorapid/PS1_known_redshift_Ia_CC_SLSN.hdf5
astrorapid/PS1_known_redshift_Ia_II_IIn_Ibc_SLSN.hdf5
astrorapid/ZTF_known_redshift.hdf5
astrorapid/ZTF_unknown_redshift.hdf5
astrorapid/__init__.py
astrorapid/classifier_metrics.py
astrorapid/classify.py
astrorapid/custom_classifier.py
astrorapid/example.py
astrorapid/fit_gaussian_process.py
astrorapid/get_custom_data.py
astrorapid/get_training_data.py
astrorapid/helpers.py
astrorapid/keras_model_no_redshift_08042020.hdf5
astrorapid/keras_model_no_redshift_pre18032020.hdf5
astrorapid/keras_model_old.hdf5
astrorapid/keras_model_with_redshift_0804020.hdf5
astrorapid/model_early_lightcurve.py
astrorapid/neural_network_model.py
astrorapid/new_example.py
astrorapid/plot_metrics.py
astrorapid/prepare_arrays.py
astrorapid/prepare_input.py
astrorapid/prepare_training_set.py
astrorapid/process_light_curves.py
astrorapid/read_snana_fits.py
astrorapid/run_on_foundation.py
astrorapid/save_ztf_data_from_osc.py
astrorapid/train_on_ztf_real_data.py
astrorapid/train_on_ztf_snana_sims.py
astrorapid/train_on_ztf_snana_sims_Ia-vs-nonIa.py
astrorapid/ANTARES_object/LAobject.py
astrorapid/ANTARES_object/__init__.py
astrorapid/ANTARES_object/constants.py
astrorapid/ANTARES_object/features/__init__.py
astrorapid/ANTARES_object/features/base.py
astrorapid-0.2.17.dist-info/LICENSE
astrorapid-0.2.17.dist-info/METADATA
astrorapid-0.2.17.dist-info/WHEEL
astrorapid-0.2.17.dist-info/entry_points.txt
astrorapid-0.2.17.dist-info/top_level.txt
astrorapid-0.2.17.dist-info/RECORD
