Metadata-Version: 2.1
Name: astrorapid
Version: 0.2.17
Summary: Real-time Automated Photometric IDentification of astronomical transients
Home-page: https://github.com/daniel-muthukrishna/astrorapid
Author: Daniel Muthukrishna
Author-email: daniel.muthukrishna@gmail.com
License: MIT
Keywords: supernova photometric light curve classification deep machine learning
Platform: UNKNOWN
Classifier: Development Status :: 4 - Beta
Classifier: Intended Audience :: Science/Research
Classifier: Topic :: Scientific/Engineering :: Astronomy
Classifier: License :: OSI Approved :: MIT License
Classifier: Programming Language :: Python :: 3
Requires-Dist: tensorflow
Requires-Dist: keras
Requires-Dist: keras-tcn
Requires-Dist: scikit-learn
Requires-Dist: astropy
Requires-Dist: pandas
Requires-Dist: extinction (==0.4)
